geometry/__init__.py
geometry/geometry.py
sigma_project-0.1.0.dist-info/METADATA
sigma_project-0.1.0.dist-info/WHEEL
sigma_project-0.1.0.dist-info/top_level.txt
sigma_project-0.1.0.dist-info/RECORD
