Metadata-Version: 2.2
Name: sigma-project
Version: 0.1.0
Summary: Add your description here
Requires-Python: >=3.13
Requires-Dist: geometry>=0.0.23
